ohmydata/__init__.py
ohmydata/easydb.py
ohmydata-0.2.dist-info/METADATA
ohmydata-0.2.dist-info/WHEEL
ohmydata-0.2.dist-info/licenses/LICENSE
ohmydata-0.2.dist-info/RECORD
